{"_meta":{"scene":"hpdi_bizdataerrorlog","formId":"hpdi_bizdataerrorlog","fullPath":"knowledge/scenarios/hpdi_bizdataerrorlog/scene_doc.json","defaultTable":"t_hpdi_bizdataerrorlog","keyGloss":"n=name t=type req=1 lk=1(isvCannotModify) tbl=非默认主表 col=非默认列名 ref=refEntity/refBasedataNumber mf=minefield<=60"},"header":{"formNumber":"hpdi_bizdataerrorlog","title":"业务数据提报异常记录","appNumber":"hpdi","cloudNumber":"HR","domain":"薪酬/业务数据处理/业务数据提报异常记录"},"basicInfo":{"businessScene":"业务数据提报异常记录 · 待补","mainEntity":"hpdi_bizdataerrorlog","relatedViews":[],"physicalTable":"t_hpdi_bizdataerrorlog（1 张物理表）","versionControl":"历史版本控制","inheritanceDepth":"待升级"},"inheritance":{},"fields":[{"n":"creator","t":"CreaterField","lk":1,"col":"fcreatorid","ref":"bos_user","mf":"系统/平台维护 · 手改破坏数据一致性"},{"n":"billno","t":"TextField"},{"n":"operatestage","t":"ComboField"},{"n":"bizitemgroup","t":"BasedataField","col":"fbizitemgroupid","ref":"hsbs_bizitemgroup"},{"n":"operatetime","t":"CreateDateField"},{"n":"notpassauditnum","t":"IntegerField"},{"n":"operatenum","t":"IntegerField"},{"n":"overinputnum","t":"IntegerField"},{"n":"notintimewindownum","t":"IntegerField"},{"n":"othernum","t":"IntegerField"},{"n":"totalnum","t":"IntegerField"},{"n":"adminorg","t":"HRAdminOrgField","col":"fadminorgid","ref":"haos_adminorghrf7","mf":"变更会级联影响下游 · 慎改"},{"n":"matchfailnum","t":"IntegerField"}],"upstream":[],"downstream":[],"invariants":{}}