{"_meta":{"scene":"homs_orgbatchchgbill_maintenance","formId":"homs_orgbatchchgbill","fullPath":"knowledge/scenarios/homs_orgbatchchgbill_maintenance/scene_doc.json","defaultTable":"t_homs_orgchgbill","keyGloss":"n=name t=type req=1 lk=1(isvCannotModify) tbl=非默认主表 col=非默认列名 ref=refEntity/refBasedataNumber mf=minefield<=60"},"header":{"formNumber":"homs_orgbatchchgbill","title":"组织调整申请","appNumber":"homs","cloudNumber":"ODC","domain":"组织发展/组织管理","modelType":"BillFormModel"},"basicInfo":{"businessScene":"组织调整申请单 · 通过申请单批量调整行政组织（变更/合并/拆分）· 走审批后落地到 haos_adminorg","mainEntity":"homs_orgbatchchgbill","relatedViews":[],"physicalTable":"t_homs_orgchgbill + t_homs_orgchgbillentry + t_homs_orgchgbill_l + t_homs_orgchgbillentry_l（4 张物理表）","versionControl":"审批单 · 单据状态流转","inheritanceDepth":"待升级"},"inheritance":{},"fields":[{"n":"billno","t":"BillNoField","req":1,"lk":1},{"n":"billstatus","t":"BillStatusField","req":1,"lk":1},{"n":"creator","t":"CreaterField","lk":1,"col":"fcreatorid","ref":"bos_user","mf":"系统/平台维护 · 手改破坏数据一致性"},{"n":"modifier","t":"ModifierField","lk":1,"col":"fmodifierid","ref":"bos_user","mf":"系统/平台维护 · 手改破坏数据一致性"},{"n":"auditor","t":"UserField","col":"fauditorid","ref":"bos_user"},{"n":"auditdate","t":"DateTimeField"},{"n":"modifytime","t":"ModifyDateField","lk":1,"mf":"系统/平台维护 · 手改破坏数据一致性"},{"n":"createtime","t":"CreateDateField","lk":1,"mf":"系统/平台维护 · 手改破坏数据一致性"},{"n":"org","t":"OrgField","req":1,"lk":1,"col":"forgid","ref":"bos_org"},{"n":"barcode","t":"TextField","col":"—"},{"n":"inputdevicetype","t":"TextField","col":"—"},{"n":"isexistsworkflow","t":"CheckBoxField"},{"n":"auditstatus","t":"BillStatusField","req":1,"lk":1},{"n":"eventeffectdate","t":"DateTimeField"},{"n":"issubmit","t":"CheckBoxField"},{"n":"add_adminorgtype","t":"BasedataField","req":1,"lk":1,"col":"—","ref":"haos_adminorgtype"},{"n":"add_corporateorg","t":"BasedataField","col":"—","ref":"hbss_lawentity"},{"n":"add_changescene","t":"BasedataField","req":1,"lk":1,"col":"—","ref":"haos_changescene"},{"n":"add_number","t":"TextField","col":"—"},{"n":"add_name","t":"MuliLangTextField","req":1,"lk":1,"col":"—"},{"n":"add_simplename","t":"MuliLangTextField","col":"—"},{"n":"add_parentorg","t":"HRAdminOrgField","req":1,"lk":1,"col":"—","ref":"haos_adminorghrf7"},{"n":"add_establishmentdate","t":"DateField","col":"—"},{"n":"add_adminorglayer","t":"BasedataField","col":"—","ref":"haos_adminorglayer"},{"n":"add_adminorgfunction","t":"BasedataField","col":"—","ref":"haos_adminorgfunction"},{"n":"add_companyarea","t":"BasedataField","col":"—","ref":"bd_country"},{"n":"add_city","t":"BasedataField","col":"—","ref":"bd_admindivision"},{"n":"add_workplace","t":"BasedataField","col":"—","ref":"hbss_workplace"},{"n":"add_parentorg_name","t":"MuliLangTextField","col":"—"},{"n":"add_adminorg","t":"BigIntField","col":"—"},{"n":"add_changereason","t":"BasedataField","col":"—","ref":"haos_orgchangereason"},{"n":"add_changetype","t":"BasedataField","col":"—","ref":"haos_orgchangetype"},{"n":"add_org","t":"OrgField","req":1,"lk":1,"col":"—","ref":"bos_org"},{"n":"add_changedescription","t":"TextField","col":"—"},{"n":"add_industrytype","t":"BasedataField","col":"—","ref":"hbss_industrytype"},{"n":"add_detailaddress","t":"MuliLangTextField","col":"—"},{"n":"add_description","t":"MuliLangTextField","col":"—"},{"n":"add_index","t":"IntegerField","col":"—"},{"n":"add_positioning","t":"MuliLangTextField","col":"—"},{"n":"add_mainduty","t":"MuliLangTextField","col":"—"},{"n":"parent_simplename","t":"MuliLangTextField","col":"—"},{"n":"parent_parentorg","t":"BasedataField","req":1,"lk":1,"col":"—","ref":"haos_adminorgbatch"},{"n":"parent_establishmentdate","t":"DateField","col":"—"},{"n":"parent_tobedisableflag","t":"CheckBoxField","col":"—"},{"n":"parent_changescene","t":"BasedataField","req":1,"lk":1,"col":"—","ref":"haos_changescene"},{"n":"parent_adminorglayer","t":"BasedataField","col":"—","ref":"haos_adminorglayer"},{"n":"parent_adminorgfunction","t":"BasedataField","col":"—","ref":"haos_adminorgfunction"},{"n":"parent_companyarea","t":"BasedataField","col":"—","ref":"bd_country"},{"n":"parent_city","t":"BasedataField","col":"—","ref":"bd_admindivision"},{"n":"parent_name","t":"MuliLangTextField","req":1,"lk":1,"col":"—"},{"n":"parent_changereason","t":"BasedataField","col":"—","ref":"haos_orgchangereason"},{"n":"parent_changetype","t":"BasedataField","col":"—","ref":"haos_orgchangetype"},{"n":"parent_workplace","t":"BasedataField","col":"—","ref":"hbss_workplace"},{"n":"parent_parentorg_name","t":"MuliLangTextField","col":"—"},{"n":"parent_oriparentorg_name","t":"TextAreaField","col":"—"},{"n":"parent_number","t":"TextField","req":1,"lk":1,"col":"—"},{"n":"parent_oriparentorg","t":"HRAdminOrgField","col":"—","ref":"haos_adminorghrf7"},{"n":"parent_adminorg","t":"HRAdminOrgField","req":1,"lk":1,"col":"—","ref":"haos_adminorghrf7"},{"n":"parent_adminorgtype","t":"BasedataField","req":1,"lk":1,"col":"—","ref":"haos_adminorgtype"},{"n":"parent_corporateorg","t":"BasedataField","col":"—","ref":"hbss_lawentity"},{"n":"parent_org","t":"OrgField","req":1,"lk":1,"col":"—","ref":"bos_org"},{"n":"parent_changedescription","t":"TextField","col":"—"},{"n":"parent_industrytype","t":"BasedataField","col":"—","ref":"hbss_industrytype"},{"n":"parent_detailaddress","t":"MuliLangTextField","col":"—"},{"n":"parent_description","t":"MuliLangTextField","col":"—"},{"n":"parent_index","t":"IntegerField","col":"—"},{"n":"parent_positioning","t":"MuliLangTextField","col":"—"},{"n":"parent_mainduty","t":"MuliLangTextField","col":"—"},{"n":"info_adminorg","t":"HRAdminOrgField","req":1,"lk":1,"col":"—","ref":"haos_adminorghrf7"},{"n":"info_name","t":"MuliLangTextField","req":1,"lk":1,"col":"—"},{"n":"info_simplename","t":"MuliLangTextField","col":"—"},{"n":"info_number","t":"TextField","req":1,"lk":1,"col":"—"},{"n":"info_establishmentdate","t":"DateField","col":"—"},{"n":"info_tobedisableflag","t":"CheckBoxField","col":"—"},{"n":"info_changescene","t":"BasedataField","req":1,"lk":1,"col":"—","ref":"haos_changescene"},{"n":"info_adminorglayer","t":"BasedataField","col":"—","ref":"haos_adminorglayer"},{"n":"info_adminorgfunction","t":"BasedataField","col":"—","ref":"haos_adminorgfunction"},{"n":"info_companyarea","t":"BasedataField","col":"—","ref":"bd_country"},{"n":"info_city","t":"BasedataField","col":"—","ref":"bd_admindivision"},{"n":"info_workplace","t":"BasedataField","col":"—","ref":"hbss_workplace"},{"n":"info_changetype","t":"BasedataField","req":1,"lk":1,"col":"—","ref":"haos_orgchangetype"},{"n":"info_changereason","t":"BasedataField","col":"—","ref":"haos_orgchangereason"},{"n":"info_oriparentorg_name","t":"TextAreaField","col":"—"},{"n":"info_parentorg","t":"BasedataField","col":"—","ref":"haos_adminorgbatch"},{"n":"info_corporateorg","t":"BasedataField","col":"—","ref":"hbss_lawentity"},{"n":"info_adminorgtype","t":"BasedataField","req":1,"lk":1,"col":"—","ref":"haos_adminorgtype"},{"n":"info_org","t":"OrgField","req":1,"lk":1,"col":"—","ref":"bos_org"},{"n":"info_changedescription","t":"TextField","col":"—"},{"n":"info_industrytype","t":"BasedataField","col":"—","ref":"hbss_industrytype"},{"n":"info_detailaddress","t":"MuliLangTextField","col":"—"},{"n":"info_description","t":"MuliLangTextField","col":"—"},{"n":"info_index","t":"IntegerField","col":"—"},{"n":"info_positioning","t":"MuliLangTextField","col":"—"},{"n":"info_mainduty","t":"MuliLangTextField","col":"—"},{"n":"disable_adminorg","t":"HRAdminOrgField","req":1,"lk":1,"col":"—","ref":"haos_adminorghrf7"},{"n":"disable_adminorgtype","t":"BasedataField","col":"—","ref":"haos_adminorgtype"},{"n":"disable_changereason","t":"BasedataField","col":"—","ref":"haos_orgchangereason"},{"n":"disable_changescene","t":"BasedataField","req":1,"lk":1,"col":"—","ref":"haos_changescene"},{"n":"disable_tobedisableflag","t":"CheckBoxField","col":"—"},{"n":"disable_changetype","t":"BasedataField","req":1,"lk":1,"col":"—","ref":"haos_orgchangetype"},{"n":"disable_oriparentorg_name","t":"TextAreaField","col":"—"},{"n":"disable_parentorg","t":"BasedataField","col":"—","ref":"haos_adminorgbatch"},{"n":"disable_org","t":"OrgField","req":1,"lk":1,"col":"—","ref":"bos_org"},{"n":"disable_changedescription","t":"TextField","col":"—"},{"n":"istodiagram","t":"CheckBoxField"},{"n":"dispatchnumber","t":"TextField"},{"n":"effdt","t":"DateField","req":1,"lk":1},{"n":"description","t":"MuliLangTextField"},{"n":"disorg","t":"HRMulAdminOrgField","col":"—"},{"n":"dispatchname","t":"MuliLangTextField"},{"n":"adminorgtype","t":"BasedataField","col":"fadminorgtypeid","ref":"haos_adminorgtype"},{"n":"changetype","t":"BasedataField","col":"fchangetypeid","ref":"haos_orgchangetype"},{"n":"number","t":"TextField"},{"n":"name","t":"MuliLangTextField"},{"n":"simplename","t":"MuliLangTextField"},{"n":"corporateorg","t":"BasedataField","col":"fcorporateorgid","ref":"hbss_lawentity"},{"n":"changescene","t":"BasedataField","col":"fchangesceneid","ref":"haos_changescene"},{"n":"parentorg","t":"HRAdminOrgField","col":"—","ref":"haos_adminorghrf7","mf":"变更会级联影响下游 · 慎改"},{"n":"establishmentdate","t":"DateField"},{"n":"adminorglayer","t":"BasedataField","col":"fadminorglayerid","ref":"haos_adminorglayer"},{"n":"adminorgfunction","t":"BasedataField","col":"fadminorgfunctionid","ref":"haos_adminorgfunction"},{"n":"companyarea","t":"BasedataField","col":"fcompanyareaid","ref":"bd_country"},{"n":"city","t":"BasedataField","col":"fcityid","ref":"bd_admindivision"},{"n":"workplace","t":"BasedataField","col":"fworkplaceid","ref":"hbss_workplace"},{"n":"changereason","t":"BasedataField","col":"fchangereasonid","ref":"haos_orgchangereason"},{"n":"oriparentorg","t":"HRAdminOrgField","col":"foriparentorgid","ref":"haos_adminorghrf7"},{"n":"adminorgid","t":"HRAdminOrgField","ref":"haos_adminorghrf7"},{"n":"changedescription","t":"TextField"},{"n":"tobedisableflag","t":"CheckBoxField"},{"n":"billtype","t":"TextField"},{"n":"addcount","t":"TextField","col":"—"},{"n":"parentcount","t":"TextField","col":"—"},{"n":"infocount","t":"TextField","col":"—"},{"n":"disablecount","t":"TextField","col":"—"},{"n":"display_chgorg","t":"CheckBoxField","col":"—"},{"n":"mergecount","t":"TextField","col":"—"},{"n":"splitcount","t":"TextField","col":"—"},{"n":"to_merge_org","t":"HRMulAdminOrgField","req":1,"lk":1,"col":"—"},{"n":"merge_target_org","t":"BasedataField","req":1,"lk":1,"col":"—","ref":"haos_adminorgbatch"},{"n":"merge_changescene","t":"BasedataField","req":1,"lk":1,"col":"—","ref":"haos_changescene"},{"n":"merge_changereason","t":"BasedataField","col":"—","ref":"haos_orgchangereason"},{"n":"merge_origin_id","t":"BigIntField","col":"—"},{"n":"merge_changetype","t":"BasedataField","req":1,"lk":1,"col":"—","ref":"haos_orgchangetype"},{"n":"merge_changedescription","t":"TextField","col":"—"},{"n":"to_split_org","t":"HRAdminOrgField","req":1,"lk":1,"col":"—","ref":"haos_adminorghrf7"},{"n":"split_target_org","t":"MulBasedataField","req":1,"lk":1,"col":"—"},{"n":"split_changescene","t":"BasedataField","req":1,"lk":1,"col":"—","ref":"haos_changescene"},{"n":"split_changereason","t":"BasedataField","col":"—","ref":"haos_orgchangereason"},{"n":"split_origin_id","t":"BigIntField","col":"—"},{"n":"split_changetype","t":"BasedataField","req":1,"lk":1,"col":"—","ref":"haos_orgchangetype"},{"n":"split_changedescription","t":"TextField","col":"—"},{"n":"terminationdetail","t":"MuliLangTextField"}],"upstream":[],"downstream":[],"invariants":{}}